Config_reader.py
python_json_config_reader-0.0.1.dist-info/licenses/LICENSE
python_json_config_reader-0.0.1.dist-info/METADATA
python_json_config_reader-0.0.1.dist-info/WHEEL
python_json_config_reader-0.0.1.dist-info/top_level.txt
python_json_config_reader-0.0.1.dist-info/RECORD
