Metadata-Version: 2.4
Name: Python-json-config-reader
Version: 0.0.1
Summary: A reader for yaml and json file in python
Author-email: Sugar51243 <1733682365@qq.com>
License: MIT License
Project-URL: Homepage, https://github.com/Sugar51243/config_reader_python
Project-URL: Issues, https://github.com/Sugar51243/config_reader_python/issues
Classifier: Programming Language :: Python :: 3
Classifier: Operating System :: OS Independent
Requires-Python: >=3.9
License-File: LICENSE
Dynamic: license-file
